mkpipe/__init__.py
mkpipe/config.py
mkpipe/main.py
mkpipe/run.py
mkpipe/functions_db/__init__.py
mkpipe/functions_db/connector_clickhouse.py
mkpipe/functions_db/connector_duckdb.py
mkpipe/functions_db/connector_postgresql.py
mkpipe/functions_db/connector_sqlite.py
mkpipe/functions_db/register_db.py
mkpipe/functions_spark/__init__.py
mkpipe/functions_spark/base_extractor.py
mkpipe/functions_spark/base_loader.py
mkpipe/functions_spark/parquet_functions.py
mkpipe/functions_spark/register_file_parser.py
mkpipe/functions_spark/session.py
mkpipe/plugins/__init__.py
mkpipe/plugins/registry.py
mkpipe/plugins/registry_jar.py
mkpipe/run_coordinators/__init__.py
mkpipe/run_coordinators/coordinator_celery.py
mkpipe/run_coordinators/coordinator_single.py
mkpipe/run_coordinators/registry.py
mkpipe/utils/__init__.py
mkpipe/utils/base_class.py
mkpipe/utils/logger.py
mkpipe-0.6.4.dist-info/licenses/LICENSE
mkpipe-0.6.4.dist-info/METADATA
mkpipe-0.6.4.dist-info/WHEEL
mkpipe-0.6.4.dist-info/entry_points.txt
mkpipe-0.6.4.dist-info/top_level.txt
mkpipe-0.6.4.dist-info/RECORD
