Metadata-Version: 2.4
Name: mkpipe
Version: 0.6.4
Summary: Core ETL pipeline framework for mkpipe.
Author: Metin Karakus
Author-email: metin_karakus@yahoo.com
License: Apache License 2.0
Classifier: Programming Language :: Python :: 3
Classifier: License :: OSI Approved :: Apache Software License
Requires-Python: >=3.8
License-File: LICENSE
Requires-Dist: psycopg2-binary>=2.9.10
Requires-Dist: pyspark>=3.5.5
Requires-Dist: pydantic>=2.10.3
Requires-Dist: PyYAML>=6.0.2
Requires-Dist: python-dotenv>=1.0.1
Requires-Dist: celery>=5.4.0
Requires-Dist: kombu>=5.4.2
Requires-Dist: sqlalchemy>=2.0.36
Requires-Dist: pysqlite3>=0.5.4
Requires-Dist: duckdb>=1.2.1
Requires-Dist: clickhouse-connect>=0.8.16
Requires-Dist: psutil>=7.0.0
Dynamic: author
Dynamic: author-email
Dynamic: classifier
Dynamic: description
Dynamic: description-content-type
Dynamic: license
Dynamic: license-file
Dynamic: requires-dist
Dynamic: requires-python
Dynamic: summary
